porousmedialab/.gitignore
porousmedialab/__init__.py
porousmedialab/analytical_solutions.py
porousmedialab/batch.py
porousmedialab/blackbox.py
porousmedialab/calibrator.py
porousmedialab/column.py
porousmedialab/desolver.py
porousmedialab/dotdict.py
porousmedialab/element.py
porousmedialab/equilibriumsolver.py
porousmedialab/lab.py
porousmedialab/metrics.py
porousmedialab/phcalc.py
porousmedialab/plotter.py
porousmedialab/richardsmodel.py
porousmedialab/saver.py
porousmedialab/sensitivity.py
porousmedialab/vg.py
porousmedialab-2.1.0.dist-info/LICENSE
porousmedialab-2.1.0.dist-info/METADATA
porousmedialab-2.1.0.dist-info/WHEEL
porousmedialab-2.1.0.dist-info/RECORD
