Metadata-Version: 2.1
Name: porousmedialab
Version: 2.1.0
Summary: Toolbox for batch and 1D reactive transport modeling in porous media aimed on easiness of use for the user without computational background
Home-page: https://github.com/biogeochemistry/PorousMediaLab
License: MIT
Keywords: modeling,reactive,transport,diffusion,advection
Author: Igor Markelov
Author-email: is.markelov@gmail.com
Requires-Python: >=3.10,<4.0
Classifier: Development Status :: 4 - Beta
Classifier: Intended Audience :: Science/Research
Classifier: License :: OSI Approved :: MIT License
Classifier: Operating System :: OS Independent
Classifier: Programming Language :: Python :: 3
Classifier: Programming Language :: Python :: 3.10
Classifier: Programming Language :: Python :: 3.11
Classifier: Programming Language :: Python :: 3.12
Classifier: Programming Language :: Python :: 3.13
Classifier: Topic :: Scientific/Engineering :: Chemistry
Classifier: Topic :: Scientific/Engineering :: Physics
Requires-Dist: h5py (>=3.0)
Requires-Dist: matplotlib (>=3.4)
Requires-Dist: numexpr (>=2.7)
Requires-Dist: numpy (>=1.20,<3)
Requires-Dist: scikit-learn (>=1.0)
Requires-Dist: scipy (>=1.10)
Requires-Dist: seaborn (>=0.11)
Project-URL: Repository, https://github.com/biogeochemistry/PorousMediaLab
